python_wgpu_torch_playground/add_1d_array.py
python_wgpu_torch_playground/add_1d_array.wgsl
python_wgpu_torch_playground/mine/min_max.py
python_wgpu_torch_playground/mine/min_max.wgsl
python_wgpu_torch_playground-0.0.1.dist-info/LICENSE
python_wgpu_torch_playground-0.0.1.dist-info/METADATA
python_wgpu_torch_playground-0.0.1.dist-info/WHEEL
python_wgpu_torch_playground-0.0.1.dist-info/top_level.txt
python_wgpu_torch_playground-0.0.1.dist-info/RECORD
