Metadata-Version: 2.1
Name: python-wgpu-torch-playground
Version: 0.0.1
Summary: A playground for Python, wgpu, and PyTorch
Author: Asher Jingkong Chen
License: MIT License
Project-URL: Homepage, https://github.com/AsherJingkongChen/python-wgpu-torch-playground/blob/main/README.md
Project-URL: Repository, https://github.com/AsherJingkongChen/python-wgpu-torch-playground.git
Keywords: python,wgpu,torch,graphics,machine learning,demo
Classifier: Development Status :: 4 - Beta
Classifier: Environment :: GPU
Classifier: License :: OSI Approved :: MIT License
Classifier: Programming Language :: Python :: 3.10
Classifier: Programming Language :: Python :: 3.11
Classifier: Programming Language :: Python :: 3.12
Classifier: Programming Language :: Python :: Implementation :: CPython
Classifier: Topic :: Multimedia :: Graphics
Classifier: Topic :: Scientific/Engineering :: Artificial Intelligence
Requires-Python: >=3.10
License-File: LICENSE
Requires-Dist: numpy >=1.26.4
Requires-Dist: torch >=2.2.2
Requires-Dist: wgpu >=0.15.0
